urljects/__init__.py
urljects/patterns.py
urljects/routemap.py
urljects/urljects.py
urljects-1.11.dist-info/DESCRIPTION.rst
urljects-1.11.dist-info/METADATA
urljects-1.11.dist-info/RECORD
urljects-1.11.dist-info/WHEEL
urljects-1.11.dist-info/metadata.json
urljects-1.11.dist-info/top_level.txt
