Metadata-Version: 2.0
Name: urljects
Version: 1.11
Summary: Django URLS DRYed.
Home-page: https://github.com/visgean/urljects
Author: Visgean Skeloru
Author-email: visgean@gmail.com
License: BSD
Keywords: urljects
Platform: UNKNOWN
Classifier: Development Status :: 5 - Production/Stable
Classifier: Intended Audience :: Developers
Classifier: License :: OSI Approved :: BSD License
Classifier: Natural Language :: English
Classifier: Programming Language :: Python :: 2
Classifier: Programming Language :: Python :: 2.6
Classifier: Programming Language :: Python :: 2.7
Classifier: Programming Language :: Python :: 3
Classifier: Programming Language :: Python :: 3.4
Classifier: Programming Language :: Python :: 3.5
Requires-Dist: django (>=1.9)
Requires-Dist: six
